casm/tools/calc/__init__.py
casm/tools/calc/commands/__init__.py
casm/tools/calc/commands/main.py
casm/tools/calc/commands/status.py
casm/tools/calc/commands/submit.py
casm/tools/calc/commands/vasp.py
casm/tools/calc/handlers/__init__.py
casm/tools/calc/handlers/_vasp.py
casm/tools/calc/methods/__init__.py
casm/tools/calc/methods/_import.py
casm/tools/calc/scripts/__init__.py
casm/tools/calc/scripts/vasp/relaxandstatic.sh
casm/tools/calc/scripts/vasp/test.sh
casm/tools/map/_StructureMappingSearch.py
casm/tools/map/__init__.py
casm/tools/map/methods.py
casm/tools/map/commands/__init__.py
casm/tools/map/commands/main.py
casm/tools/map/commands/search.py
casm/tools/map/commands/search2.py
casm/tools/map/commands/write.py
casm/tools/shared/__init__.py
casm/tools/shared/ase_utils.py
casm/tools/shared/contexts.py
casm/tools/shared/file_utils.py
casm/tools/shared/json_io.py
casm/tools/shared/structure_io.py
casm/tools/shared/text_io.py
casm_tools-2.0a2.dist-info/licenses/LICENSE
casm_tools-2.0a2.dist-info/METADATA
casm_tools-2.0a2.dist-info/WHEEL
casm_tools-2.0a2.dist-info/entry_points.txt
casm_tools-2.0a2.dist-info/top_level.txt
casm_tools-2.0a2.dist-info/RECORD
