Metadata-Version: 2.4
Name: casm-tools
Version: 2.0a2
Summary: CASM command line tools
Author-email: CASM developers <casm-developers@lists.engr.ucsb.edu>
License-Expression: LGPL-2.1-or-later
Project-URL: Homepage, https://prisms-center.github.io/CASMcode_docs/
Project-URL: Repository, https://github.com/prisms-center/CASMcode_tools
Classifier: Development Status :: 3 - Alpha
Classifier: Programming Language :: Python :: 3
Classifier: Topic :: Scientific/Engineering
Requires-Python: <3.14,>=3.9
License-File: LICENSE
Requires-Dist: libcasm-xtal>=2.2.0
Requires-Dist: libcasm-mapping>=2.3.0
Requires-Dist: libcasm-configuration>=2.2.0
Requires-Dist: numpy
Requires-Dist: tabulate
Provides-Extra: ase
Requires-Dist: ase; extra == "ase"
Dynamic: license-file
